gameoflifeemulator/__init__.py
gameoflifeemulator/gameoflife.py
gameoflifeemulator-0.0.1.data/scripts/gameoflife
gameoflifeemulator-0.0.1.dist-info/LICENSE
gameoflifeemulator-0.0.1.dist-info/METADATA
gameoflifeemulator-0.0.1.dist-info/WHEEL
gameoflifeemulator-0.0.1.dist-info/top_level.txt
gameoflifeemulator-0.0.1.dist-info/RECORD
