Metadata-Version: 2.1
Name: gameoflifeemulator
Version: 0.0.1
Summary: The game of life emulator
Home-page: https://github.com/parsampsh/gameoflife
Author: parsa shahmaleki
Author-email: parsampsh@gmail.com
License: UNKNOWN
Platform: UNKNOWN
Classifier: Programming Language :: Python :: 3
Classifier: Operating System :: OS Independent
Requires-Python: >=3.6
